<?xml version="1.0" encoding="UTF-8" standalone="no"?>
<diagram program="umlet" version="14.3.0">
  <zoom_level>14</zoom_level>
  <element>
    <id>UMLActor</id>
    <coordinates>
      <x>238</x>
      <y>0</y>
      <w>84</w>
      <h>154</h>
    </coordinates>
    <panel_attributes>Actor</panel_attributes>
    <additional_attributes/>
  </element>
  <element>
    <id>Relation</id>
    <coordinates>
      <x>266</x>
      <y>84</y>
      <w>42</w>
      <h>1008</h>
    </coordinates>
    <panel_attributes>lt=.</panel_attributes>
    <additional_attributes>10.0;10.0;10.0;700.0</additional_attributes>
  </element>
  <element>
    <id>Relation</id>
    <coordinates>
      <x>266</x>
      <y>168</y>
      <w>420</w>
      <h>56</h>
    </coordinates>
    <panel_attributes>lt=&lt;&lt;&lt;-
deleteEvent(event)</panel_attributes>
    <additional_attributes>280.0;20.0;10.0;20.0</additional_attributes>
  </element>
  <element>
    <id>UMLGeneric</id>
    <coordinates>
      <x>462</x>
      <y>28</y>
      <w>336</w>
      <h>70</h>
    </coordinates>
    <panel_attributes>CatERingAppManager.eventManager:
EventManager</panel_attributes>
    <additional_attributes/>
  </element>
  <element>
    <id>Relation</id>
    <coordinates>
      <x>658</x>
      <y>84</y>
      <w>42</w>
      <h>1008</h>
    </coordinates>
    <panel_attributes>lt=.</panel_attributes>
    <additional_attributes>10.0;10.0;10.0;700.0</additional_attributes>
  </element>
  <element>
    <id>UMLGeneric</id>
    <coordinates>
      <x>658</x>
      <y>168</y>
      <w>28</w>
      <h>882</h>
    </coordinates>
    <panel_attributes/>
    <additional_attributes/>
  </element>
  <element>
    <id>Relation</id>
    <coordinates>
      <x>266</x>
      <y>1008</y>
      <w>420</w>
      <h>56</h>
    </coordinates>
    <panel_attributes>lt=&lt;.
</panel_attributes>
    <additional_attributes>10.0;20.0;280.0;20.0</additional_attributes>
  </element>
  <element>
    <id>UMLFrame</id>
    <coordinates>
      <x>0</x>
      <y>322</y>
      <w>1624</w>
      <h>742</h>
    </coordinates>
    <panel_attributes>alt 

[event == null 
|| user != event.getOwner()]
--

-.
fontsize=11
</panel_attributes>
    <additional_attributes/>
  </element>
  <element>
    <id>Relation</id>
    <coordinates>
      <x>266</x>
      <y>364</y>
      <w>420</w>
      <h>56</h>
    </coordinates>
    <panel_attributes>lt=&lt;.
throw UseCaseLogicException</panel_attributes>
    <additional_attributes>10.0;20.0;280.0;20.0</additional_attributes>
  </element>
  <element>
    <id>Relation</id>
    <coordinates>
      <x>672</x>
      <y>546</y>
      <w>518</w>
      <h>56</h>
    </coordinates>
    <panel_attributes>lt=&lt;&lt;&lt;-
setEnded(true)</panel_attributes>
    <additional_attributes>350.0;20.0;10.0;20.0</additional_attributes>
  </element>
  <element>
    <id>UMLGeneric</id>
    <coordinates>
      <x>1246</x>
      <y>28</y>
      <w>210</w>
      <h>70</h>
    </coordinates>
    <panel_attributes>EventManager.events:
List&lt;Event&gt;</panel_attributes>
    <additional_attributes/>
  </element>
  <element>
    <id>Relation</id>
    <coordinates>
      <x>672</x>
      <y>812</y>
      <w>644</w>
      <h>56</h>
    </coordinates>
    <panel_attributes>lt=&lt;&lt;&lt;-
remove(event)</panel_attributes>
    <additional_attributes>440.0;20.0;10.0;20.0</additional_attributes>
  </element>
  <element>
    <id>UMLFrame</id>
    <coordinates>
      <x>490</x>
      <y>882</y>
      <w>1092</w>
      <h>98</h>
    </coordinates>
    <panel_attributes>for each
rec in receivers
fg=magenta</panel_attributes>
    <additional_attributes/>
  </element>
  <element>
    <id>Relation</id>
    <coordinates>
      <x>658</x>
      <y>910</y>
      <w>896</w>
      <h>56</h>
    </coordinates>
    <panel_attributes>lt=&lt;&lt;&lt;-
notifyEventDeleted(event)
fg=magenta</panel_attributes>
    <additional_attributes>620.0;20.0;10.0;20.0</additional_attributes>
  </element>
  <element>
    <id>Relation</id>
    <coordinates>
      <x>1526</x>
      <y>84</y>
      <w>42</w>
      <h>1008</h>
    </coordinates>
    <panel_attributes>lt=.
fg=magenta</panel_attributes>
    <additional_attributes>10.0;10.0;10.0;700.0</additional_attributes>
  </element>
  <element>
    <id>UMLGeneric</id>
    <coordinates>
      <x>1470</x>
      <y>28</y>
      <w>252</w>
      <h>70</h>
    </coordinates>
    <panel_attributes>receivers:
EventManagerEventReceiver
fg=magenta</panel_attributes>
    <additional_attributes/>
  </element>
  <element>
    <id>Relation</id>
    <coordinates>
      <x>1288</x>
      <y>84</y>
      <w>42</w>
      <h>812</h>
    </coordinates>
    <panel_attributes>lt=.</panel_attributes>
    <additional_attributes>10.0;10.0;10.0;560.0</additional_attributes>
  </element>
  <element>
    <id>UMLGeneric</id>
    <coordinates>
      <x>1288</x>
      <y>812</y>
      <w>28</w>
      <h>56</h>
    </coordinates>
    <panel_attributes/>
    <additional_attributes/>
  </element>
  <element>
    <id>Relation</id>
    <coordinates>
      <x>672</x>
      <y>224</y>
      <w>280</w>
      <h>56</h>
    </coordinates>
    <panel_attributes>lt=&lt;&lt;&lt;-
user = getCurrentUser( )</panel_attributes>
    <additional_attributes>180.0;20.0;10.0;20.0</additional_attributes>
  </element>
  <element>
    <id>Relation</id>
    <coordinates>
      <x>672</x>
      <y>266</y>
      <w>280</w>
      <h>42</h>
    </coordinates>
    <panel_attributes>lt=&lt;.</panel_attributes>
    <additional_attributes>10.0;10.0;180.0;10.0</additional_attributes>
  </element>
  <element>
    <id>Relation</id>
    <coordinates>
      <x>924</x>
      <y>84</y>
      <w>42</w>
      <h>238</h>
    </coordinates>
    <panel_attributes>lt=.</panel_attributes>
    <additional_attributes>10.0;10.0;10.0;150.0</additional_attributes>
  </element>
  <element>
    <id>UMLGeneric</id>
    <coordinates>
      <x>924</x>
      <y>238</y>
      <w>28</w>
      <h>56</h>
    </coordinates>
    <panel_attributes/>
    <additional_attributes/>
  </element>
  <element>
    <id>UMLGeneric</id>
    <coordinates>
      <x>812</x>
      <y>28</y>
      <w>322</w>
      <h>70</h>
    </coordinates>
    <panel_attributes>CatERingAppManager.userManager:
UserManager
</panel_attributes>
    <additional_attributes/>
  </element>
  <element>
    <id>UMLGeneric</id>
    <coordinates>
      <x>1526</x>
      <y>924</y>
      <w>28</w>
      <h>28</h>
    </coordinates>
    <panel_attributes>fg=magenta</panel_attributes>
    <additional_attributes/>
  </element>
  <element>
    <id>UMLGeneric</id>
    <coordinates>
      <x>1148</x>
      <y>28</y>
      <w>84</w>
      <h>70</h>
    </coordinates>
    <panel_attributes>event:
Event</panel_attributes>
    <additional_attributes/>
  </element>
  <element>
    <id>Relation</id>
    <coordinates>
      <x>1162</x>
      <y>84</y>
      <w>42</w>
      <h>602</h>
    </coordinates>
    <panel_attributes>lt=.</panel_attributes>
    <additional_attributes>10.0;10.0;10.0;410.0</additional_attributes>
  </element>
  <element>
    <id>UMLGeneric</id>
    <coordinates>
      <x>1162</x>
      <y>560</y>
      <w>28</w>
      <h>98</h>
    </coordinates>
    <panel_attributes/>
    <additional_attributes/>
  </element>
  <element>
    <id>Relation</id>
    <coordinates>
      <x>672</x>
      <y>602</y>
      <w>518</w>
      <h>56</h>
    </coordinates>
    <panel_attributes>lt=&lt;&lt;&lt;-
setPublished(false)</panel_attributes>
    <additional_attributes>350.0;20.0;10.0;20.0</additional_attributes>
  </element>
</diagram>
